flask_socketio/__init__.py
flask_socketio/namespace.py
flask_socketio/test_client.py
my_Flask_SocketIO-4.3.2.dist-info/LICENSE
my_Flask_SocketIO-4.3.2.dist-info/METADATA
my_Flask_SocketIO-4.3.2.dist-info/WHEEL
my_Flask_SocketIO-4.3.2.dist-info/top_level.txt
my_Flask_SocketIO-4.3.2.dist-info/RECORD
